Metadata-Version: 2.1
Name: prda-middleware
Version: 0.0.2
Summary: prda_middleware
Home-page: UNKNOWN
Author: Jan Krupa
License: MIT
Platform: UNKNOWN
